setup.py
funnier/__init__.py
funnier/text.py
funnier.egg-info/PKG-INFO
funnier.egg-info/SOURCES.txt
funnier.egg-info/dependency_links.txt
funnier.egg-info/not-zip-safe
funnier.egg-info/requires.txt
funnier.egg-info/top_level.txt